cinema4d_mcp/__init__.py
cinema4d_mcp/config.py
cinema4d_mcp/server.py
cinema4d_mcp/utils.py
orange1_cinema4d_mcp-0.1.2.dist-info/METADATA
orange1_cinema4d_mcp-0.1.2.dist-info/WHEEL
orange1_cinema4d_mcp-0.1.2.dist-info/entry_points.txt
orange1_cinema4d_mcp-0.1.2.dist-info/top_level.txt
orange1_cinema4d_mcp-0.1.2.dist-info/RECORD
